django_jalali_date_modern-1.0.0.dist-info/licenses/LICENSE
jalali_date/__init__.py
jalali_date/admin.py
jalali_date/fields.py
jalali_date/settings.py
jalali_date/utils.py
jalali_date/widgets.py
jalali_date/static/.DS_Store
jalali_date/static/admin/.DS_Store
jalali_date/static/admin/jalalidatepicker.min.css
jalali_date/static/admin/jalalidatepicker.min.js
jalali_date/static/admin/jquery.ui.datepicker.jalali/.DS_Store
jalali_date/static/admin/jquery.ui.datepicker.jalali/def.htm
jalali_date/static/admin/jquery.ui.datepicker.jalali/default.htm
jalali_date/static/admin/jquery.ui.datepicker.jalali/jalalidatepicker.min.css
jalali_date/static/admin/jquery.ui.datepicker.jalali/jalalidatepicker.min.js
jalali_date/static/admin/jquery.ui.datepicker.jalali/scripts/calendar.all.js
jalali_date/static/admin/jquery.ui.datepicker.jalali/scripts/calendar.js
jalali_date/static/admin/jquery.ui.datepicker.jalali/scripts/jquery-1.10.2.min.js
jalali_date/static/admin/jquery.ui.datepicker.jalali/scripts/jquery-1.10.2.min.map
jalali_date/static/admin/jquery.ui.datepicker.jalali/scripts/jquery.ui.core.js
jalali_date/static/admin/jquery.ui.datepicker.jalali/scripts/jquery.ui.datepicker-cc-fa.js
jalali_date/static/admin/jquery.ui.datepicker.jalali/scripts/jquery.ui.datepicker-cc.js
jalali_date/static/admin/jquery.ui.datepicker.jalali/themes/base/jquery-ui.min.css
jalali_date/static/admin/jquery.ui.datepicker.jalali/themes/base/images/ui-icons_444444_256x240.png
jalali_date/static/admin/jquery.ui.datepicker.jalali/themes/base/images/ui-icons_555555_256x240.png
jalali_date/static/admin/jquery.ui.datepicker.jalali/themes/base/images/ui-icons_777620_256x240.png
jalali_date/static/admin/jquery.ui.datepicker.jalali/themes/base/images/ui-icons_777777_256x240.png
jalali_date/static/admin/jquery.ui.datepicker.jalali/themes/base/images/ui-icons_cc0000_256x240.png
jalali_date/static/admin/jquery.ui.datepicker.jalali/themes/base/images/ui-icons_ffffff_256x240.png
jalali_date/static/admin/js/django_jalali..js
jalali_date/static/admin/js/django_jalali.min.js
django_jalali_date_modern-1.0.0.dist-info/METADATA
django_jalali_date_modern-1.0.0.dist-info/WHEEL
django_jalali_date_modern-1.0.0.dist-info/top_level.txt
django_jalali_date_modern-1.0.0.dist-info/RECORD
