Metadata-Version: 2.4
Name: django-jalali-date-modern
Version: 1.0.0
Summary: Jalali Date support for user interface. Easy conversion of DateTimeFiled to JalaliDateTimeField within the admin site, views, forms and templates. This project uses the original django-jalali-date but swapping the datepicker library.
Home-page: http://github.com/a-roomana/django-jalali-date
Download-URL: https://pypi.python.org/pypi/django-jalali-date/
Author: Karim Akhavan Azari
Author-email: erfan226@gmail.com
License: MIT
Keywords: django jalali date
Platform: any
Classifier: Environment :: Web Environment
Classifier: Intended Audience :: Developers
Classifier: Operating System :: OS Independent
Classifier: Topic :: Software Development :: Libraries :: Application Frameworks
Classifier: Topic :: Software Development :: Libraries :: Python Modules
Classifier: Programming Language :: Python
Classifier: Programming Language :: Python :: 3.8
Classifier: Programming Language :: Python :: 3.9
Classifier: Programming Language :: Python :: 3.10
Classifier: Programming Language :: Python :: 3.11
Classifier: Framework :: Django
Classifier: Framework :: Django :: 2.2
Classifier: Framework :: Django :: 3.2
Classifier: Framework :: Django :: 4.2
Classifier: Framework :: Django :: 5.0
Requires-Python: >=3
License-File: LICENSE
Requires-Dist: django
Requires-Dist: jdatetime
Dynamic: author
Dynamic: author-email
Dynamic: classifier
Dynamic: description
Dynamic: description-content-type
Dynamic: download-url
Dynamic: home-page
Dynamic: keywords
Dynamic: license
Dynamic: license-file
Dynamic: platform
Dynamic: requires-dist
Dynamic: requires-python
Dynamic: summary
